{"data":[{"area_id":32272,"type":1,"shape":0,"lat":51.324497,"lng":4.259047,"radius":810,"level":2,"updated_at":1473658579,"begin_at":0,"end_at":0,"name":"Doel Nuclear Power Station","city":"Beveren","country":"BE","runway_length":0,"runway_show":0,"points":"","url":"","address":"","is_web":0},{"area_id":4650,"type":0,"shape":0,"lat":51.200315,"lng":2.876089,"radius":2146,"level":2,"updated_at":1447945800,"begin_at":0,"end_at":0,"name":"Ostend-Bruges International Airport","city":"Ostend","country":"BE","runway_length":0,"runway_show":0,"points":"","url":"","address":"","is_web":0},{"area_id":31810,"type":1,"shape":0,"lat":51.193272,"lng":3.180583,"radius":500,"level":2,"updated_at":1447945800,"begin_at":0,"end_at":0,"name":"Jan Breydel Stadium","city":"Bruges","country":"BE","runway_length":0,"runway_show":0,"points":"","url":"","address":"","is_web":0},{"area_id":1089,"type":0,"shape":0,"lat":51.188746,"lng":4.460873,"radius":854,"level":2,"updated_at":1447945800,"begin_at":0,"end_at":0,"name":"Antwerp International (Deurne) Airport","city":"Antwerp","country":"BE","runway_length":0,"runway_show":0,"points":"","url":"","address":"","is_web":0},{"area_id":9769,"type":0,"shape":0,"lat":51.169724,"lng":5.471111,"radius":1609,"level":2,"updated_at":1447945800,"begin_at":0,"end_at":0,"name":"Kleine Brogel Air Base","city":"Peer","country":"BE","runway_length":0,"runway_show":0,"points":"","url":"","address":"","is_web":0},{"area_id":31869,"type":1,"shape":0,"lat":51.005,"lng":5.533333,"radius":500,"level":2,"updated_at":1447945800,"begin_at":0,"end_at":0,"name":"Cristal Arena","city":"Genk","country":"BE","runway_length":0,"runway_show":0,"points":"","url":"","address":"","is_web":0},{"area_id":5601,"type":0,"shape":0,"lat":50.970417,"lng":5.375056,"radius":448,"level":2,"updated_at":1447945800,"begin_at":0,"end_at":0,"name":"Kiewit Airfield Hasselt Airport","city":"Hasselt","country":"BE","runway_length":0,"runway_show":0,"points":"","url":"","address":"","is_web":0},{"area_id":3463,"type":0,"shape":0,"lat":50.900997,"lng":4.485574,"radius":2885,"level":2,"updated_at":1474341464,"begin_at":0,"end_at":0,"name":"Brussels Airport","city":"Brussels","country":"BE","runway_length":0,"runway_show":0,"points":"","url":"","address":"","is_web":0},{"area_id":31652,"type":1,"shape":0,"lat":50.895706,"lng":4.334083,"radius":500,"level":2,"updated_at":1447945800,"begin_at":0,"end_at":0,"name":"King Baudouin Stadium","city":"Brussels","country":"BE","runway_length":0,"runway_show":0,"points":"","url":"","address":"","is_web":0},{"area_id":31822,"type":1,"shape":0,"lat":50.834194,"lng":4.298361,"radius":500,"level":2,"updated_at":1447945800,"begin_at":0,"end_at":0,"name":"Constant Vanden Stock Stadium","city":"Brussels","country":"BE","runway_length":0,"runway_show":0,"points":"","url":"","address":"","is_web":0},{"area_id":4922,"type":0,"shape":0,"lat":50.818288,"lng":3.207897,"radius":1168,"level":2,"updated_at":1447945800,"begin_at":0,"end_at":0,"name":"Wevelgem Airport","city":"Wevelgem","country":"BE","runway_length":0,"runway_show":0,"points":"","url":"","address":"","is_web":0},{"area_id":3487,"type":0,"shape":0,"lat":50.7892,"lng":5.1944,"radius":1658,"level":2,"updated_at":1447945800,"begin_at":0,"end_at":0,"name":"Bost Airport","city":"Bost","country":"BE","runway_length":0,"runway_show":0,"points":"","url":"","address":"","is_web":0},{"area_id":9768,"type":0,"shape":0,"lat":50.756873,"lng":4.76799,"radius":1653,"level":2,"updated_at":1447945800,"begin_at":0,"end_at":0,"name":"Beauvechain Air Base","city":"Beauvechain","country":"BE","runway_length":0,"runway_show":0,"points":"","url":"","address":"","is_web":0},{"area_id":3784,"type":0,"shape":0,"lat":50.640397,"lng":5.446882,"radius":2270,"level":2,"updated_at":1447945800,"begin_at":0,"end_at":0,"name":"Liège Airport","city":"Liège","country":"BE","runway_length":0,"runway_show":0,"points":"","url":"","address":"","is_web":0},{"area_id":31795,"type":1,"shape":0,"lat":50.609908,"lng":5.543344,"radius":500,"level":2,"updated_at":1447945800,"begin_at":0,"end_at":0,"name":"Stade Maurice Dufrasne","city":"Liege","country":"BE","runway_length":0,"runway_show":0,"points":"","url":"","address":"","is_web":0},{"area_id":9770,"type":0,"shape":0,"lat":50.577226,"lng":3.838455,"radius":1526,"level":2,"updated_at":1447945800,"begin_at":0,"end_at":0,"name":"Chievres AB","city":"Lens","country":"BE","runway_length":0,"runway_show":0,"points":"","url":"","address":"","is_web":0},{"area_id":32273,"type":1,"shape":0,"lat":50.534844,"lng":5.271034,"radius":786,"level":2,"updated_at":1473658623,"begin_at":0,"end_at":0,"name":"Centrale Nucléaire de Tihange","city":"Huy","country":"BE","runway_length":0,"runway_show":0,"points":"","url":"","address":"","is_web":0},{"area_id":8767,"type":0,"shape":0,"lat":50.53148,"lng":3.495748,"radius":598,"level":2,"updated_at":1447945800,"begin_at":0,"end_at":0,"name":"Tournai/Maubray Airport","city":"Tournai","country":"BE","runway_length":0,"runway_show":0,"points":"","url":"","address":"","is_web":0},{"area_id":5637,"type":0,"shape":0,"lat":50.489401,"lng":4.769622,"radius":580,"level":2,"updated_at":1447945800,"begin_at":0,"end_at":0,"name":"Suarlée Airport","city":"Namur","country":"BE","runway_length":0,"runway_show":0,"points":"","url":"","address":"","is_web":0},{"area_id":2018,"type":0,"shape":0,"lat":50.462251,"lng":4.45931,"radius":2124,"level":2,"updated_at":1447945800,"begin_at":0,"end_at":0,"name":"Brussels South Charleroi Airport","city":"Brussels","country":"BE","runway_length":0,"runway_show":0,"points":"","url":"","address":"","is_web":0},{"area_id":9771,"type":0,"shape":0,"lat":50.241494,"lng":4.648715,"radius":1792,"level":2,"updated_at":1447945800,"begin_at":0,"end_at":0,"name":"Florennes Air Base","city":"Florennes","country":"BE","runway_length":0,"runway_show":0,"points":"","url":"","address":"","is_web":0}],"status":"200"}