{"data":[{"area_id":5392,"type":0,"shape":0,"lat":25.614772,"lng":55.939635,"radius":2768,"level":2,"updated_at":1447945800,"begin_at":0,"end_at":0,"name":"Ras Al Khaimah International Airport","city":"Ras Al Khaimah","country":"AE","runway_length":0,"runway_show":0,"points":"","url":"","address":"","is_web":0},{"area_id":3610,"type":0,"shape":0,"lat":25.614097,"lng":56.244863,"radius":466,"level":2,"updated_at":1447945800,"begin_at":0,"end_at":0,"name":"Dibba Airport","city":"Dibba Al-Baya","country":"AE","runway_length":0,"runway_show":0,"points":"","url":"","address":"","is_web":0},{"area_id":8282,"type":0,"shape":0,"lat":25.328436,"lng":55.513624,"radius":2715,"level":2,"updated_at":1447945800,"begin_at":0,"end_at":0,"name":"Sharjah International Airport","city":"Sharjah","country":"AE","runway_length":0,"runway_show":0,"points":"","url":"","address":"","is_web":0},{"area_id":769,"type":0,"shape":0,"lat":25.250069,"lng":55.368585,"radius":3688,"level":2,"updated_at":1447945800,"begin_at":0,"end_at":0,"name":"Dubai International Airport","city":"Dubai","country":"AE","runway_length":0,"runway_show":0,"points":"","url":"","address":"","is_web":0},{"area_id":336,"type":0,"shape":0,"lat":25.109722,"lng":56.328317,"radius":3211,"level":2,"updated_at":1447945800,"begin_at":0,"end_at":0,"name":"Fujairah International Airport","city":"","country":"AE","runway_length":0,"runway_show":0,"points":"","url":"","address":"","is_web":0},{"area_id":4226,"type":0,"shape":0,"lat":25.026978,"lng":55.36768,"radius":2394,"level":2,"updated_at":1447945800,"begin_at":0,"end_at":0,"name":"Al Minhad Air Base Airport","city":"Dubai","country":"AE","runway_length":0,"runway_show":0,"points":"","url":"","address":"","is_web":0},{"area_id":761,"type":0,"shape":0,"lat":24.892338,"lng":55.158981,"radius":3046,"level":2,"updated_at":1447945800,"begin_at":0,"end_at":0,"name":"Al Maktoum International Airport","city":"Dubai","country":"AE","runway_length":0,"runway_show":0,"points":"","url":"","address":"","is_web":0},{"area_id":1234,"type":0,"shape":0,"lat":24.444907,"lng":54.651783,"radius":4260,"level":2,"updated_at":1447945800,"begin_at":0,"end_at":0,"name":"Abu Dhabi International Airport","city":"Abu Dhabi","country":"AE","runway_length":0,"runway_show":0,"points":"","url":"","address":"","is_web":0},{"area_id":1318,"type":0,"shape":0,"lat":24.428333,"lng":54.458057,"radius":1987,"level":2,"updated_at":1447945800,"begin_at":0,"end_at":0,"name":"Port lotniczy Batin","city":"Abu Dhabi","country":"AE","runway_length":0,"runway_show":0,"points":"","url":"","address":"","is_web":0},{"area_id":798,"type":0,"shape":0,"lat":24.261331,"lng":55.61531,"radius":3651,"level":2,"updated_at":1447945800,"begin_at":0,"end_at":0,"name":"Al Ain International Airport","city":"Al Ain","country":"AE","runway_length":0,"runway_show":0,"points":"","url":"","address":"","is_web":0},{"area_id":573,"type":0,"shape":0,"lat":24.236788,"lng":54.550434,"radius":3619,"level":2,"updated_at":1447945800,"begin_at":0,"end_at":0,"name":"Al Dhafra Air Base Airport","city":"Abu Dhabi","country":"AE","runway_length":0,"runway_show":0,"points":"","url":"","address":"","is_web":0}],"status":"200"}