{"data":[{"area_id":2026,"type":0,"shape":0,"lat":12.47647,"lng":-61.472562,"radius":454,"level":2,"updated_at":1447945800,"begin_at":0,"end_at":0,"name":"Lauriston Airport","city":"Carriacou Island","country":"GD","runway_length":0,"runway_show":0,"points":"","url":"","address":"","is_web":0},{"area_id":2394,"type":0,"shape":0,"lat":12.004167,"lng":-61.786111,"radius":1529,"level":2,"updated_at":1447945800,"begin_at":0,"end_at":0,"name":"Point Salines International Airport","city":"Saint George's","country":"GD","runway_length":0,"runway_show":0,"points":"","url":"","address":"","is_web":0}],"status":"200"}